ofxstatement_ru/__init__.py
ofxstatement_ru/alfabank.py
ofxstatement_ru/avangard.py
ofxstatement_ru/raiffeisen.py
ofxstatement_ru/sberbank_csv.py
ofxstatement_ru/sberbank_txt.py
ofxstatement_ru/tinkoff.py
ofxstatement_ru/vtb.py
ofxstatement_ru-0.5.0.dist-info/LICENSE
ofxstatement_ru-0.5.0.dist-info/METADATA
ofxstatement_ru-0.5.0.dist-info/WHEEL
ofxstatement_ru-0.5.0.dist-info/entry_points.txt
ofxstatement_ru-0.5.0.dist-info/RECORD
