Metadata-Version: 2.1
Name: ofxstatement-ru
Version: 0.5.0
Summary: ofxstatement plugins for Russian banks
Home-page: https://github.com/senz/ofxstatement-ru
License: GPL-3.0
Keywords: ofxstatement,bank,plugin,russian,sberbank,tinkoff,alfabank,vtb,raiffeisen,avangard
Author: Konstantin Romanov
Author-email: kosta-codes@proton.me
Maintainer: Konstantin Romanov
Maintainer-email: kosta-codes@proton.me
Requires-Python: >=3.9,<4.0
Classifier: Development Status :: 3 - Alpha
Classifier: License :: OSI Approved :: GNU General Public License v3 (GPLv3)
Classifier: Natural Language :: Russian
Classifier: Operating System :: OS Independent
Classifier: Programming Language :: Python
Classifier: Programming Language :: Python :: 3
Classifier: Programming Language :: Python :: 3.9
Classifier: Programming Language :: Python :: 3.10
Classifier: Programming Language :: Python :: 3.11
Classifier: Programming Language :: Python :: 3.12
Classifier: Programming Language :: Python :: 3.13
Provides-Extra: dev
Requires-Dist: ofxstatement (>=0.9.1,<0.10.0)
Project-URL: Repository, https://github.com/senz/ofxstatement-ru
